{
  "generated_utc": "2026-07-22T19:50:24+00:00",
  "market": {
    "vxn_used": 26.63,
    "vix_used": 16.93,
    "vix3m_used": 19.69,
    "curve": {
      "vxn": 26.66,
      "vxn_date": "2026-07-21",
      "vxn_chg": -0.065545,
      "vxn_ref": 26.66,
      "vix": 17.05,
      "vix_date": "2026-07-21",
      "vix_chg": -0.085791,
      "vix_ref": 17.05,
      "vix3m": 19.59,
      "vix3m_date": "2026-07-21",
      "vix3m_chg": -0.039706,
      "vix3m_ref": 19.59
    },
    "quotes": {
      "vxn": {
        "price": 26.63,
        "prev_close": 26.66,
        "change_pct": -0.001125,
        "session": "regular",
        "regular_price": 26.63,
        "regular_change": -0.001125,
        "ext_price": null,
        "ext_change": null,
        "time": "2026-07-22T19:35:17+00:00"
      },
      "vix": {
        "price": 16.93,
        "prev_close": 17.05,
        "change_pct": -0.007038,
        "session": "regular",
        "regular_price": 16.93,
        "regular_change": -0.007038,
        "ext_price": null,
        "ext_change": null,
        "time": "2026-07-22T19:35:16+00:00"
      },
      "vix3m": {
        "price": 19.69,
        "prev_close": 19.59,
        "change_pct": 0.005105,
        "session": "regular",
        "regular_price": 19.69,
        "regular_change": 0.005105,
        "ext_price": null,
        "ext_change": null,
        "time": "2026-07-22T19:35:16+00:00"
      },
      "ndx": {
        "price": 29052.58,
        "prev_close": 29155.18,
        "change_pct": -0.003519,
        "session": "regular",
        "regular_price": 29043.057,
        "regular_change": -0.003846,
        "ext_price": null,
        "ext_change": null,
        "time": "2026-07-22T19:50:26+00:00"
      },
      "tqqq": {
        "price": 70.61,
        "prev_close": 71.37,
        "change_pct": -0.010649,
        "session": "regular",
        "regular_price": 70.61,
        "regular_change": -0.010649,
        "ext_price": null,
        "ext_change": null,
        "time": "2026-07-22T19:50:25+00:00"
      },
      "sqqq": {
        "price": 40.7501,
        "prev_close": 40.31,
        "change_pct": 0.010918,
        "session": "regular",
        "regular_price": 40.7501,
        "regular_change": 0.010918,
        "ext_price": null,
        "ext_change": null,
        "time": "2026-07-22T19:50:25+00:00"
      },
      "qqq": {
        "price": 706.475,
        "prev_close": 708.97,
        "change_pct": -0.003519,
        "session": "regular",
        "regular_price": 706.475,
        "regular_change": -0.003519,
        "ext_price": null,
        "ext_change": null,
        "time": "2026-07-22T19:50:26+00:00"
      },
      "spy": {
        "price": 747.81,
        "prev_close": 748.28,
        "change_pct": -0.000628,
        "session": "regular",
        "regular_price": 747.81,
        "regular_change": -0.000628,
        "ext_price": null,
        "ext_change": null,
        "time": "2026-07-22T19:50:26+00:00"
      },
      "upro": {
        "price": 141.59,
        "prev_close": 141.89,
        "change_pct": -0.002114,
        "session": "regular",
        "regular_price": 141.59,
        "regular_change": -0.002114,
        "ext_price": null,
        "ext_change": null,
        "time": "2026-07-22T19:50:14+00:00"
      },
      "spxu": {
        "price": 37.12,
        "prev_close": 37.04,
        "change_pct": 0.00216,
        "session": "regular",
        "regular_price": 37.12,
        "regular_change": 0.00216,
        "ext_price": null,
        "ext_change": null,
        "time": "2026-07-22T19:50:24+00:00"
      },
      "spx": {
        "price": 7502.76,
        "prev_close": 7509.2,
        "change_pct": -0.000858,
        "session": "regular",
        "regular_price": 7502.76,
        "regular_change": -0.000858,
        "ext_price": null,
        "ext_change": null,
        "time": "2026-07-22T19:50:27+00:00"
      }
    }
  },
  "derived": {
    "contango": 0.163024,
    "yc_spread": null,
    "regime": "contango"
  },
  "cboe_refreshed": false,
  "official": {
    "date": "2026-07-21",
    "position": "LONG_TQQQ",
    "signal": "LONG_TQQQ",
    "open_pnl": 0.439346,
    "equity": 51555953.82,
    "entry_date": "2026-04-10",
    "entry_price": 49.057,
    "open_pnl_live": true
  },
  "note": "VXN/VIX/VIX3M are CBOE end-of-day (re-fetched only after the ~5:30pm ET post; cached intraday) with Yahoo intraday overrides. ETF quotes are Yahoo intraday (~5-15 min delayed). Signals finalize on the daily close and trade the next market open."
}