{
  "generated_utc": "2026-07-23T14:00:36+00:00",
  "market": {
    "vxn_used": 28.12,
    "vix_used": 18.75,
    "vix3m_used": 20.71,
    "curve": {
      "vxn": 26.74,
      "vxn_date": "2026-07-22",
      "vxn_chg": 0.003001,
      "vxn_ref": 26.74,
      "vix": 16.64,
      "vix_date": "2026-07-22",
      "vix_chg": -0.024047,
      "vix_ref": 16.64,
      "vix3m": 19.54,
      "vix3m_date": "2026-07-22",
      "vix3m_chg": -0.002552,
      "vix3m_ref": 19.54
    },
    "quotes": {
      "vxn": {
        "price": 28.12,
        "prev_close": 26.74,
        "change_pct": 0.051608,
        "session": "regular",
        "asof_date": "2026-07-23",
        "regular_price": 28.12,
        "regular_change": 0.051608,
        "ext_price": null,
        "ext_change": null,
        "reg_time": "2026-07-23T13:45:32+00:00",
        "time": "2026-07-23T13:45:32+00:00"
      },
      "vix": {
        "price": 18.75,
        "prev_close": 16.64,
        "change_pct": 0.126803,
        "session": "regular",
        "asof_date": "2026-07-23",
        "regular_price": 18.75,
        "regular_change": 0.122754,
        "ext_price": null,
        "ext_change": null,
        "reg_time": "2026-07-23T13:45:31+00:00",
        "time": "2026-07-23T13:45:31+00:00"
      },
      "vix3m": {
        "price": 20.71,
        "prev_close": 19.54,
        "change_pct": 0.059877,
        "session": "regular",
        "asof_date": "2026-07-23",
        "regular_price": 20.71,
        "regular_change": 0.059877,
        "ext_price": null,
        "ext_change": null,
        "reg_time": "2026-07-23T13:45:31+00:00",
        "time": "2026-07-23T13:45:31+00:00"
      },
      "ndx": {
        "price": 28616.37,
        "prev_close": 28998.1,
        "change_pct": -0.013164,
        "session": "regular",
        "asof_date": "2026-07-23",
        "regular_price": 28599.8633,
        "regular_change": -0.013733,
        "ext_price": null,
        "ext_change": null,
        "reg_time": "2026-07-23T14:00:36+00:00",
        "time": "2026-07-23T14:00:41+00:00"
      },
      "tqqq": {
        "price": 67.4,
        "prev_close": 70.15,
        "change_pct": -0.039202,
        "session": "regular",
        "asof_date": "2026-07-23",
        "regular_price": 67.4,
        "regular_change": -0.039202,
        "ext_price": null,
        "ext_change": null,
        "reg_time": "2026-07-23T14:00:39+00:00",
        "time": "2026-07-23T14:00:39+00:00"
      },
      "sqqq": {
        "price": 42.62,
        "prev_close": 41.019,
        "change_pct": 0.039031,
        "session": "regular",
        "asof_date": "2026-07-23",
        "regular_price": 42.62,
        "regular_change": 0.039031,
        "ext_price": null,
        "ext_change": null,
        "reg_time": "2026-07-23T14:00:41+00:00",
        "time": "2026-07-23T14:00:41+00:00"
      },
      "qqq": {
        "price": 695.69,
        "prev_close": 704.97,
        "change_pct": -0.013164,
        "session": "regular",
        "asof_date": "2026-07-23",
        "regular_price": 695.69,
        "regular_change": -0.013164,
        "ext_price": null,
        "ext_change": null,
        "reg_time": "2026-07-23T14:00:41+00:00",
        "time": "2026-07-23T14:00:41+00:00"
      },
      "spy": {
        "price": 740.54,
        "prev_close": 747.36,
        "change_pct": -0.009125,
        "session": "regular",
        "asof_date": "2026-07-23",
        "regular_price": 740.54,
        "regular_change": -0.009125,
        "ext_price": null,
        "ext_change": null,
        "reg_time": "2026-07-23T14:00:42+00:00",
        "time": "2026-07-23T14:00:42+00:00"
      },
      "upro": {
        "price": 137.3399,
        "prev_close": 141.23,
        "change_pct": -0.027544,
        "session": "regular",
        "asof_date": "2026-07-23",
        "regular_price": 137.3399,
        "regular_change": -0.027544,
        "ext_price": null,
        "ext_change": null,
        "reg_time": "2026-07-23T14:00:37+00:00",
        "time": "2026-07-23T14:00:37+00:00"
      },
      "spxu": {
        "price": 38.23,
        "prev_close": 37.19,
        "change_pct": 0.027964,
        "session": "regular",
        "asof_date": "2026-07-23",
        "regular_price": 38.23,
        "regular_change": 0.027964,
        "ext_price": null,
        "ext_change": null,
        "reg_time": "2026-07-23T14:00:42+00:00",
        "time": "2026-07-23T14:00:42+00:00"
      },
      "spx": {
        "price": 7429.25,
        "prev_close": 7499.4399,
        "change_pct": -0.009359,
        "session": "regular",
        "asof_date": "2026-07-23",
        "regular_price": 7429.25,
        "regular_change": -0.009359,
        "ext_price": null,
        "ext_change": null,
        "reg_time": "2026-07-23T14:00:45+00:00",
        "time": "2026-07-23T14:00:45+00:00"
      }
    }
  },
  "derived": {
    "contango": 0.104533,
    "contango_live": true,
    "contango_asof": "2026-07-23",
    "yc_spread": null,
    "regime": "contango"
  },
  "cboe_refreshed": false,
  "official": {
    "date": "2026-07-22",
    "position": "LONG_TQQQ",
    "signal": "LONG_TQQQ",
    "open_pnl": 0.373912,
    "equity": 50768582.32,
    "entry_date": "2026-04-10",
    "entry_price": 49.057,
    "open_pnl_live": true
  },
  "note": "VXN/VIX/VIX3M are CBOE end-of-day (re-fetched only after the ~5:30pm ET post; cached intraday) with Yahoo intraday overrides. ETF quotes are Yahoo intraday (~5-15 min delayed). Signals finalize on the daily close and trade the next market open."
}